trade_safety/__init__.py
trade_safety/api/__init__.py
trade_safety/api/router.py
trade_safety/factories.py
trade_safety/managers.py
trade_safety/models.py
trade_safety/preview_service.py
trade_safety/prompts.py
trade_safety/py.typed
trade_safety/reddit_extract_text_service.py
trade_safety/repositories/__init__.py
trade_safety/repositories/trade_safety_repository.py
trade_safety/schemas.py
trade_safety/service.py
trade_safety/settings.py
trade_safety/twitter_extract_text_service.py
trade_safety-1.11.0.dist-info/METADATA
trade_safety-1.11.0.dist-info/WHEEL
trade_safety-1.11.0.dist-info/RECORD
