Metadata-Version: 2.4
Name: trade-safety
Version: 1.11.0
Summary: AI-powered safety analysis for K-pop merchandise trading
License: Apache-2.0
Keywords: kpop,merchandise,trade,safety,llm,scam-detection
Author: AIoIA, Inc.
Author-email: devops@aioia.ai
Requires-Python: >=3.10,<3.13
Classifier: License :: OSI Approved :: Apache Software License
Classifier: Programming Language :: Python :: 3
Classifier: Programming Language :: Python :: 3.10
Classifier: Programming Language :: Python :: 3.11
Classifier: Programming Language :: Python :: 3.12
Requires-Dist: aioia-core (>=2.0.0,<3.0.0)
Requires-Dist: alembic (>=1.13.0,<2.0.0)
Requires-Dist: fastapi (>=0.115.0,<0.116.0)
Requires-Dist: langchain (>=0.1,<1)
Requires-Dist: langchain-community (>=0.1,<1)
Requires-Dist: langchain-openai (>=0.1,<1)
Requires-Dist: openai (>=1.0.0)
Requires-Dist: psycopg2-binary (>=2.9.0,<3.0.0)
Requires-Dist: pydantic (>=2.5.0,<3.0.0)
Requires-Dist: pydantic-settings (>=2.1.0,<3.0.0)
Requires-Dist: python-dotenv (>=1.0.0,<2.0.0)
Requires-Dist: sqlalchemy (>=2.0.0,<3.0.0)
